album2video/PathTool.py
album2video/__init__.py
album2video/__main__.py
album2video/config.ini
album2video/config.py
album2video/fonts/Calibri.otf
album2video-1.0.0.dist-info/LICENSE
album2video-1.0.0.dist-info/METADATA
album2video-1.0.0.dist-info/WHEEL
album2video-1.0.0.dist-info/RECORD
