Metadata-Version: 2.1
Name: album2video
Version: 1.0.0
Summary: album2video creates an albumvideo(with img as bg) from tracks w/ timestamp output
License: Unlicense
Author: Alice Katherine
Author-email: hoxas@live.com
Requires-Python: >=3.11,<4.0
Classifier: License :: OSI Approved
Classifier: Programming Language :: Python :: 3
Classifier: Programming Language :: Python :: 3.11
Classifier: Programming Language :: Python :: 3.12
Requires-Dist: docopt (>=0.6.2,<0.7.0)
Requires-Dist: moviepy (>=2.1.2,<3.0.0)
